deeplake/__init__.py
labeldb/__init__.py
labelstore/__init__.py
labelstore-0.0.1.dist-info/METADATA
labelstore-0.0.1.dist-info/WHEEL
labelstore-0.0.1.dist-info/top_level.txt
labelstore-0.0.1.dist-info/RECORD
